agent_os2/DEVELOPING_GUIDE.md
agent_os2/__init__.py
agent_os2/agent_settings.json
agent_os2/changelog.md
agent_os2/model_settings_example.json
agent_os2/agent_os/base_agent.py
agent_os2/agent_os/flow.py
agent_os2/agent_os/utility.py
agent_os2/agent_os/visualize.py
agent_os2/agent_os/base_model/base_api.py
agent_os2/agent_os/base_model/builtin_config.py
agent_os2/agent_os/base_model/model_processor.py
agent_os2/agent_os/base_model/models_price.json
agent_os2/agent_os/base_model/processor_registry.py
agent_os2/agent_os/base_model/utility.py
agent_os2/assistant/__init__.py
agent_os2/assistant/agents/design_confirm/publish_event.py
agent_os2/assistant/agents/design_confirm/request_analysis.py
agent_os2/assistant/agents/design_confirm/user_input_get.py
agent_os2/assistant/flows/design_confirm_flow.py
agent_os2/assistant/flows/orchestrator_flow.py
agent_os2/assistant/flows/tools/semantic_search_flow.py
agent_os2/assistant/prompts/prompt_geter.py
agent_os2/assistant/prompts/roles.py
agent_os2/assistant/prompts/Agent心智模型/base_agent.txt
agent_os2/assistant/prompts/Agent心智模型/内置命令.txt
agent_os2/assistant/prompts/Agent心智模型/动态编排.txt
agent_os2/assistant/prompts/Agent心智模型/外部输入.txt
agent_os2/assistant/prompts/Agent心智模型/批处理.txt
agent_os2/assistant/prompts/Agent心智模型/提示词模板系统.txt
agent_os2/assistant/prompts/Agent心智模型/数据处理管线.txt
agent_os2/assistant/prompts/Agent心智模型/模型请求.txt
agent_os2/assistant/prompts/Agent心智模型/模型调用失败的重试机制.txt
agent_os2/assistant/prompts/Agent心智模型/流式输出实时消息.txt
agent_os2/assistant/prompts/Agent心智模型/调度职责.txt
agent_os2/assistant/prompts/Agent心智模型/上下文系统/构建时上下文.txt
agent_os2/assistant/prompts/Agent心智模型/上下文系统/运行时上下文.txt
agent_os2/assistant/prompts/Agent心智模型/可重写方法/adjust_prompt_after_failure方法.txt
agent_os2/assistant/prompts/Agent心智模型/可重写方法/apply_command方法.txt
agent_os2/assistant/prompts/Agent心智模型/可重写方法/get_context_value方法.txt
agent_os2/assistant/prompts/Agent心智模型/可重写方法/merge_source_context方法.txt
agent_os2/assistant/prompts/Agent心智模型/可重写方法/parse_model_result方法.txt
agent_os2-1.2.5.dist-info/METADATA
agent_os2-1.2.5.dist-info/WHEEL
agent_os2-1.2.5.dist-info/top_level.txt
agent_os2-1.2.5.dist-info/RECORD
