Metadata-Version: 2.4
Name: agent_os2
Version: 1.2.5
Summary: 面向LLM的工作流图嵌套调度框架
License: MIT
Requires-Python: >=3.12
Requires-Dist: aiohttp>=3.11.14
Requires-Dist: requests>=2.32.3
Requires-Dist: google-genai[aiohttp]>=1.27.0
Requires-Dist: pillow>=11.1.0
Requires-Dist: PyYAML>=6.0
Requires-Dist: tiktoken>=0.9.0
